xnetwork/__init__.py
xnetwork-0.9.dist-info/LICENSE
xnetwork-0.9.dist-info/METADATA
xnetwork-0.9.dist-info/WHEEL
xnetwork-0.9.dist-info/top_level.txt
xnetwork-0.9.dist-info/RECORD
